[
  {
    "case": {
      "genre": "horror",
      "mood": "eerie",
      "player_class": "alchemist",
      "target_difficulty": "hard"
    },
    "level": {
      "theme": "Abandoned Alchemy Lab",
      "setting": "Subterranean Catacombs",
      "player_weapon": "Acid Vial",
      "player_weapon_damage": 25,
      "player_health": 80,
      "encounters": [
        {
          "location": "Storage Vault",
          "enemy": {
            "name": "Hollowed Apprentice",
            "health": 50,
            "damage": 15,
            "weakness": "Acid Vial"
          },
          "hazard": "Leaking Chlorine Gas",
          "pickup": {
            "name": "Catalyst Catalyst",
            "effect": "Enhances acidic compounds"
          },
          "trigger": "Stepping on the pressure plate releases the Apprentice"
        },
        {
          "location": "Transmutation Hall",
          "enemy": {
            "name": "Corrupted Homunculus",
            "health": 70,
            "damage": 20,
            "weakness": "Catalyst Catalyst"
          },
          "hazard": "Spreading Necrotic Mold",
          "pickup": {
            "name": "Silver Nitrate Solution",
            "effect": "Stabilizes volatile mixtures"
          },
          "trigger": "Activating the centrifuge draws the Homunculus from the pipes"
        },
        {
          "location": "Forbidden Archive",
          "enemy": {
            "name": "Specter of the Master",
            "health": 100,
            "damage": 30,
            "weakness": "Silver Nitrate Solution"
          },
          "hazard": "Arcane Shadow Void",
          "pickup": {
            "name": "Soul Binding Seal",
            "effect": "Weakens ethereal entities"
          },
          "trigger": "Unlocking the archive door summons the Specter to guard the final sanctum"
        }
      ],
      "boss": {
        "name": "The Blighted Primordial",
        "health": 300,
        "damage": 50,
        "weakness": "Soul Binding Seal",
        "victory_condition": "Seal the rift with the Soul Binding Seal"
      },
      "objective": "Purify the Alchemical Blight",
      "reward": "Philosopher's Stone"
    }
  },
  {
    "case": {
      "genre": "horror",
      "mood": "ominous",
      "player_class": "pyromancer",
      "target_difficulty": "brutal"
    },
    "level": {
      "theme": "Eldritch Decay",
      "setting": "Abandoned Ritual Grounds",
      "player_weapon": "Flamethrower",
      "player_weapon_damage": 50,
      "player_health": 100,
      "encounters": [
        {
          "location": "Crypt Entrance",
          "enemy": {
            "name": "Shadow Stalker",
            "health": 100,
            "damage": 30,
            "weakness": "Flamethrower"
          },
          "hazard": "Falling spikes from the ceiling",
          "pickup": {
            "name": "Iron Key",
            "effect": "Unlocks the heavy iron gate to the Inner Sanctum"
          },
          "trigger": "Eliminating the Stalker deactivates the barrier, allowing passage to the Inner Sanctum"
        },
        {
          "location": "Ritual Corridor",
          "enemy": {
            "name": "Bloated Corpse",
            "health": 150,
            "damage": 40,
            "weakness": "Iron Key"
          },
          "hazard": "Toxic gas vents",
          "pickup": {
            "name": "Purified Oil",
            "effect": "Enhances fire damage output"
          },
          "trigger": "Defeating the Corpse causes the floor to retract, revealing the hidden alcove with the salt"
        },
        {
          "location": "Altar Dais",
          "enemy": {
            "name": "Wraith",
            "health": 200,
            "damage": 50,
            "weakness": "Purified Oil"
          },
          "hazard": "Shrinking vision radius",
          "pickup": {
            "name": "Sun-Blessed Salt",
            "effect": "Allows player to bypass the Lich's void armor"
          },
          "trigger": "Exorcising the Wraith causes the Altar to awaken and summon the Boss"
        }
      ],
      "boss": {
        "name": "Void-Touched Lich",
        "health": 500,
        "damage": 80,
        "weakness": "Sun-Blessed Salt",
        "victory_condition": "Purify the defiled altar with the Sun-Blessed Salt"
      },
      "objective": "Cleanse the defiled altar to stop the spread of rot",
      "reward": "Eternal Flame Essence"
    }
  },
  {
    "case": {
      "genre": "horror",
      "mood": "tense",
      "player_class": "shadowblade",
      "target_difficulty": "medium"
    },
    "level": {
      "theme": "Dark Gothic Horror",
      "setting": "Abandoned Victorian Manor",
      "player_weapon": "Shadow Dagger",
      "player_weapon_damage": 50,
      "player_health": 100,
      "encounters": [
        {
          "location": "Corridor of Whispers",
          "enemy": {
            "name": "Shadow Stalker",
            "health": 100,
            "damage": 20,
            "weakness": "Shadow Dagger"
          },
          "hazard": "Moving shadows that reduce visibility",
          "pickup": {
            "name": "Silvered Key",
            "effect": "Allows access to the Sanctum"
          },
          "trigger": "Taking the key awakens the next horror"
        },
        {
          "location": "Storage Basement",
          "enemy": {
            "name": "Flesh Amalgam",
            "health": 150,
            "damage": 25,
            "weakness": "Silvered Key"
          },
          "hazard": "Acid leaking from ceiling pipes",
          "pickup": {
            "name": "Sunlight Core",
            "effect": "Can burn away shadow entities and expose hidden paths"
          },
          "trigger": "Defeating this enemy triggers the alarm leading to the boss door"
        },
        {
          "location": "The Inner Gate",
          "enemy": {
            "name": "Phantom Guard",
            "health": 200,
            "damage": 30,
            "weakness": "Shadow Dagger"
          },
          "hazard": "Pressure sensitive floor traps",
          "pickup": {
            "name": "Shadow Essence",
            "effect": "Grants short burst of shadow speed"
          },
          "trigger": "Killing the guard opens the Boss chamber doors"
        }
      ],
      "boss": {
        "name": "The Echoing Stalker",
        "health": 500,
        "damage": 40,
        "weakness": "Sunlight Core",
        "victory_condition": "Use the Sunlight Core to burn away the shadow veil and make him vulnerable to critical strikes"
      },
      "objective": "Infiltrate the Cursed Manor and banish the Echoing Stalker to restore the void",
      "reward": "Amulet of Void"
    }
  },
  {
    "case": {
      "genre": "horror",
      "mood": "desolate",
      "player_class": "ranger",
      "target_difficulty": "hard"
    },
    "level": {
      "theme": "Horror",
      "setting": "Abandoned research facility",
      "player_weapon": "Silver-tipped longbow",
      "player_weapon_damage": 15,
      "player_health": 50,
      "encounters": [
        {
          "location": "Laboratory Annex",
          "enemy": {
            "name": "Shadow Crawler",
            "health": 40,
            "damage": 10,
            "weakness": "Silver-tipped longbow"
          },
          "hazard": "Toxic gas leaks",
          "pickup": {
            "name": "Fragile Lantern",
            "effect": "Provides illumination to reveal hidden paths"
          },
          "trigger": "Entering the main laboratory corridor triggers the lockdown"
        },
        {
          "location": "Ventilation Shaft",
          "enemy": {
            "name": "Hollowed Sentinel",
            "health": 60,
            "damage": 15,
            "weakness": "Fragile Lantern light"
          },
          "hazard": "Falling debris",
          "pickup": {
            "name": "Alchemical Solvent",
            "effect": "Corrodes dense shadow armor"
          },
          "trigger": "Clearing the path through the shaft opens the ventilation hatch"
        },
        {
          "location": "Mainframe Core",
          "enemy": {
            "name": "Void Stalker",
            "health": 80,
            "damage": 20,
            "weakness": "Alchemical Solvent"
          },
          "hazard": "Pitch black darkness",
          "pickup": {
            "name": "Sun-Stone Relic",
            "effect": "Emits high-intensity purifying energy"
          },
          "trigger": "Accessing the security terminal initiates the boss encounter sequence"
        }
      ],
      "boss": {
        "name": "The Abyssal Construct",
        "health": 200,
        "damage": 25,
        "weakness": "Sun-Stone Relic",
        "victory_condition": "Infuse the Sun-Stone Relic into the core terminal"
      },
      "objective": "Purify the facility and defeat the source of the corruption",
      "reward": "Safe passage and restoration of the facility power grid"
    }
  },
  {
    "case": {
      "genre": "horror",
      "mood": "mysterious",
      "player_class": "necromancer",
      "target_difficulty": "easy"
    },
    "level": {
      "theme": "Horror",
      "setting": "Victorian Catacombs",
      "player_weapon": "Soul Scythe",
      "player_weapon_damage": 25,
      "player_health": 100,
      "encounters": [
        {
          "location": "Crypt Entrance",
          "enemy": {
            "name": "Bone Crawler",
            "health": 20,
            "damage": 5,
            "weakness": "Soul Scythe"
          },
          "hazard": "Flickering shadow flames",
          "pickup": {
            "name": "Silver Dust",
            "effect": "Damages spectral entities"
          },
          "trigger": "Opening the main crypt gate starts the hunt"
        },
        {
          "location": "Whispering Hallway",
          "enemy": {
            "name": "Hollow Knight",
            "health": 25,
            "damage": 7,
            "weakness": "Silver Dust"
          },
          "hazard": "Falling debris from the ceiling",
          "pickup": {
            "name": "Blessed Amulet",
            "effect": "Reveals hidden passages"
          },
          "trigger": "Retrieving the Silver Dust reveals the passage to the hall"
        },
        {
          "location": "Inner Sanctum",
          "enemy": {
            "name": "Dark Familiar",
            "health": 30,
            "damage": 10,
            "weakness": "Blessed Amulet"
          },
          "hazard": "Cursed fog that saps stamina",
          "pickup": {
            "name": "Sun-Blessed Relic",
            "effect": "Inflicts massive damage to void-born bosses"
          },
          "trigger": "Wearing the Blessed Amulet dispels the fog, revealing the boss arena"
        }
      ],
      "boss": {
        "name": "The Abyssal Warden",
        "health": 60,
        "damage": 15,
        "weakness": "Sun-Blessed Relic",
        "victory_condition": "Seal the void rift using the Sun-Blessed Relic"
      },
      "objective": "Banish the Abyssal Warden from the catacombs",
      "reward": "The Necromancer's Grimoire of Light"
    }
  },
  {
    "case": {
      "genre": "horror",
      "mood": "chaotic",
      "player_class": "berserker",
      "target_difficulty": "brutal"
    },
    "level": {
      "theme": "Flesh and Machinery",
      "setting": "Abandoned Asylum",
      "player_weapon": "Rusty Cleaver",
      "player_weapon_damage": 25,
      "player_health": 100,
      "encounters": [
        {
          "location": "Dark Hallway",
          "enemy": {
            "name": "Twitching Husk",
            "health": 80,
            "damage": 20,
            "weakness": "Rusty Cleaver"
          },
          "hazard": "Falling debris",
          "pickup": {
            "name": "Adrenaline Syringe",
            "effect": "Temporary speed boost"
          },
          "trigger": "Blood trail leading to the boiler room"
        },
        {
          "location": "Boiler Room",
          "enemy": {
            "name": "Scuttling Flesh-Mass",
            "health": 120,
            "damage": 30,
            "weakness": "Adrenaline Syringe"
          },
          "hazard": "Toxic gas leak",
          "pickup": {
            "name": "Corroded Key",
            "effect": "Unlocks the vault door"
          },
          "trigger": "Loud metal clanging signaling the approach to the morgue"
        },
        {
          "location": "The Morgue",
          "enemy": {
            "name": "Armored Abomination",
            "health": 200,
            "damage": 40,
            "weakness": "Corroded Key"
          },
          "hazard": "Moving mechanical blades",
          "pickup": {
            "name": "Cursed Totem",
            "effect": "Reveals boss vulnerability"
          },
          "trigger": "Alarm system activates and seals the path to the catacombs"
        }
      ],
      "boss": {
        "name": "The Surgeon",
        "health": 300,
        "damage": 50,
        "weakness": "Cursed Totem",
        "victory_condition": "Decapitate him"
      },
      "objective": "Escape the asylum by killing the surgeon",
      "reward": "Eternal Bloodlust"
    }
  },
  {
    "case": {
      "genre": "horror",
      "mood": "serene",
      "player_class": "warden",
      "target_difficulty": "medium"
    },
    "level": {
      "theme": "Ethereal serenity",
      "setting": "Sunken Library",
      "player_weapon": "Soul-Lantern",
      "player_weapon_damage": 15,
      "player_health": 100,
      "encounters": [
        {
          "location": "Grand Hall",
          "enemy": {
            "name": "Echoing Shade",
            "health": 40,
            "damage": 10,
            "weakness": "Soul-Lantern light"
          },
          "hazard": "Falling bookshelves",
          "pickup": {
            "name": "Incense Vial",
            "effect": "Slows enemy movement"
          },
          "trigger": "Defeat triggers the ventilation to clear the mist for the next room."
        },
        {
          "location": "Reading Nook",
          "enemy": {
            "name": "Hollow Automaton",
            "health": 50,
            "damage": 15,
            "weakness": "Incense Vial"
          },
          "hazard": "Creaking floorboards",
          "pickup": {
            "name": "Silver Key",
            "effect": "Unlocks the archives gate"
          },
          "trigger": "Opening the gate allows entry into the final wing."
        },
        {
          "location": "Archives Entryway",
          "enemy": {
            "name": "Whispering Guardian",
            "health": 60,
            "damage": 15,
            "weakness": "Soul-Lantern light"
          },
          "hazard": "Cold draft",
          "pickup": {
            "name": "Ghostly Essence",
            "effect": "Restores stamina"
          },
          "trigger": "Defeating the guardian unseals the door to the boss arena."
        }
      ],
      "boss": {
        "name": "The Librarian Spirit",
        "health": 100,
        "damage": 20,
        "weakness": "Silver Key",
        "victory_condition": "Seal the spirit using the Silver Key."
      },
      "objective": "Retrieve the Lost Tome while pacifying the library spirits.",
      "reward": "Forbidden Knowledge scroll"
    }
  },
  {
    "case": {
      "genre": "horror",
      "mood": "whimsical",
      "player_class": "illusionist",
      "target_difficulty": "easy"
    },
    "level": {
      "theme": "Cursed Nursery",
      "setting": "Haunted Toybox Manor",
      "player_weapon": "Mirror Prism",
      "player_weapon_damage": 20,
      "player_health": 100,
      "encounters": [
        {
          "location": "Dusty Hallway",
          "enemy": {
            "name": "Ghostly Rocking Horse",
            "health": 30,
            "damage": 10,
            "weakness": "Mirror Prism"
          },
          "hazard": "Creaking floorboards that echo shrieks",
          "pickup": {
            "name": "Magical Glue",
            "effect": "Stuns enemies for two turns"
          },
          "trigger": "Defeating the rocking horse drops a key to the playroom"
        },
        {
          "location": "Playroom",
          "enemy": {
            "name": "Animated Teddy Bear",
            "health": 40,
            "damage": 15,
            "weakness": "Magical Glue"
          },
          "hazard": "Floating toy building blocks",
          "pickup": {
            "name": "Bottled Laughter",
            "effect": "Dispels magical gloom"
          },
          "trigger": "Unlocking the playroom chest summons the shadow marionette"
        },
        {
          "location": "Nursery",
          "enemy": {
            "name": "Shadow Marionette",
            "health": 35,
            "damage": 10,
            "weakness": "Mirror Prism"
          },
          "hazard": "Spinning crib mobile",
          "pickup": {
            "name": "Shiny Gear",
            "effect": "Increases illusion attack speed"
          },
          "trigger": "Exorcising the marionette opens the door to the boss arena"
        }
      ],
      "boss": {
        "name": "Jolly Jack-in-the-Box",
        "health": 150,
        "damage": 25,
        "weakness": "The Bottled Laughter collected in the nursery",
        "victory_condition": "Shatter the main winding crank"
      },
      "objective": "Retrieve the Heart of the Clockwork Jester",
      "reward": "The Giggling Pendant"
    }
  },
  {
    "case": {
      "genre": "steampunk",
      "mood": "chaotic",
      "player_class": "engineer",
      "target_difficulty": "medium"
    },
    "level": {
      "theme": "Chaotic Steampunk",
      "setting": "Subterranean Clockwork Factory",
      "player_weapon": "Wrench Cannon",
      "player_weapon_damage": 15,
      "player_health": 100,
      "encounters": [
        {
          "location": "Boiler Room",
          "enemy": {
            "name": "Clockwork Sentry",
            "health": 30,
            "damage": 10,
            "weakness": "Wrench Cannon"
          },
          "hazard": "High-pressure steam bursts",
          "pickup": {
            "name": "Grease Vial",
            "effect": "Lubricates mechanical joints"
          },
          "trigger": "Sabotaging the main steam valve forces the security alarm to alert the next sector"
        },
        {
          "location": "Assembly Line",
          "enemy": {
            "name": "Brass Scrapper",
            "health": 40,
            "damage": 15,
            "weakness": "Grease Vial"
          },
          "hazard": "Moving gear-laden conveyor belts",
          "pickup": {
            "name": "Overclock Key",
            "effect": "Increases weapon fire rate"
          },
          "trigger": "Stopping the assembly line overrides the security hatch to the central turbine"
        },
        {
          "location": "Turbine Room",
          "enemy": {
            "name": "Automated Piston Guard",
            "health": 50,
            "damage": 20,
            "weakness": "Overclock Key"
          },
          "hazard": "Erratic electrical arcs",
          "pickup": {
            "name": "Master Shutoff Core",
            "effect": "Disables core mechanical systems"
          },
          "trigger": "Overloading the primary generator forces the Clockwork Heart to emerge from the floor"
        }
      ],
      "boss": {
        "name": "The Clockwork Heart",
        "health": 150,
        "damage": 30,
        "weakness": "Master Shutoff Core",
        "victory_condition": "Insert the Master Shutoff Core into the main processor port"
      },
      "objective": "Disable the rogue Clockwork Heart before the facility undergoes a catastrophic steam explosion",
      "reward": "Steam-Powered Exo-Suit"
    }
  },
  {
    "case": {
      "genre": "steampunk",
      "mood": "mysterious",
      "player_class": "artificer",
      "target_difficulty": "hard"
    },
    "level": {
      "theme": "Mysterious steampunk industrial decay",
      "setting": "A decaying brass-plated clockwork city suspended in dense, toxic clouds",
      "player_weapon": "Clockwork Wrench-Hammer",
      "player_weapon_damage": 15,
      "player_health": 100,
      "encounters": [
        {
          "location": "Central Steam Duct",
          "enemy": {
            "name": "Steam-Vent Crawler",
            "health": 50,
            "damage": 10,
            "weakness": "Clockwork Wrench-Hammer"
          },
          "hazard": "High-pressure steam pipes",
          "pickup": {
            "name": "Copper Conduit",
            "effect": "Conducts intense electrical surges"
          },
          "trigger": "Defeating the crawler retracts the barrier leading to the Gear Forge"
        },
        {
          "location": "The Gear Forge",
          "enemy": {
            "name": "Brass Sentinel",
            "health": 70,
            "damage": 15,
            "weakness": "Copper Conduit"
          },
          "hazard": "Rotating gear floors that deal contact damage",
          "pickup": {
            "name": "Overclocked Valve",
            "effect": "Forces machinery to operate at unstable, maximum capacity"
          },
          "trigger": "The sentinel's destruction powers the rusted lift to the Apex Chamber"
        },
        {
          "location": "The Apex Chamber",
          "enemy": {
            "name": "Void-Touched Automaton",
            "health": 90,
            "damage": 20,
            "weakness": "Overclocked Valve"
          },
          "hazard": "Low-oxygen environment causing stamina degradation",
          "pickup": {
            "name": "Core Stabilizer Key",
            "effect": "Temporarily slows the boss's reaction time"
          },
          "trigger": "Eliminating the automaton initiates the boss sequence for the Grand Architect"
        }
      ],
      "boss": {
        "name": "The Grand Architect",
        "health": 200,
        "damage": 30,
        "weakness": "Overclocked Valve",
        "victory_condition": "Use the Overclocked Valve to overload his core, causing a permanent mechanical shutdown"
      },
      "objective": "Disable the city's central core to prevent a city-wide atmospheric collapse",
      "reward": "The blueprints to the Eternal Clockwork Engine and infinite steam pressure"
    }
  },
  {
    "case": {
      "genre": "steampunk",
      "mood": "whimsical",
      "player_class": "alchemist",
      "target_difficulty": "easy"
    },
    "level": {
      "theme": "Whimsical steampunk",
      "setting": "Brass-and-steam conservatory",
      "player_weapon": "Acidic Flasks",
      "player_weapon_damage": 10,
      "player_health": 100,
      "encounters": [
        {
          "location": "Petal-Gear Greenhouse",
          "enemy": {
            "name": "Brass Beetle",
            "health": 15,
            "damage": 2,
            "weakness": "Acidic Flasks"
          },
          "hazard": "High-pressure steam leaks",
          "pickup": {
            "name": "Concentrated Rust-Solvent",
            "effect": "Corrodes metallic armor"
          },
          "trigger": "Defeating the beetle unlocks the ventilation gate leading to the next zone."
        },
        {
          "location": "Iron Vine Overlook",
          "enemy": {
            "name": "Steam-Powered Snail",
            "health": 20,
            "damage": 3,
            "weakness": "Concentrated Rust-Solvent"
          },
          "hazard": "Slippery grease trails",
          "pickup": {
            "name": "Super-Conductive Copper Coil",
            "effect": "Disrupts electrical currents"
          },
          "trigger": "Stopping the snail reveals a hidden pressure plate to access the Spire."
        },
        {
          "location": "The Whistling Spire",
          "enemy": {
            "name": "Clockwork Sparrow",
            "health": 25,
            "damage": 4,
            "weakness": "Super-Conductive Copper Coil"
          },
          "hazard": "Spinning gear blades",
          "pickup": {
            "name": "Chrono-Stabilizer Fluid",
            "effect": "Slows time for clockwork mechanisms"
          },
          "trigger": "Clipping the sparrow's wings exposes the master controller for the final confrontation."
        }
      ],
      "boss": {
        "name": "The Grand Automat-Archivist",
        "health": 50,
        "damage": 8,
        "weakness": "Chrono-Stabilizer Fluid",
        "victory_condition": "Freeze the master clock core to cease all mechanical hostilities."
      },
      "objective": "Disable the rogue automaton controllers in the conservatory.",
      "reward": "The Alchemist's Master Gear-Key"
    }
  },
  {
    "case": {
      "genre": "steampunk",
      "mood": "tense",
      "player_class": "rogue",
      "target_difficulty": "brutal"
    },
    "level": {
      "theme": "Steampunk",
      "setting": "Smog-choked clockwork factory",
      "player_weapon": "Brass Dagger",
      "player_weapon_damage": 20,
      "player_health": 100,
      "encounters": [
        {
          "location": "Assembly Floor",
          "enemy": {
            "name": "Steam Automaton",
            "health": 50,
            "damage": 30,
            "weakness": "Brass Dagger"
          },
          "hazard": "High-pressure pipe burst",
          "pickup": {
            "name": "Hydraulic Wrench",
            "effect": "Slows mechanical movement"
          },
          "trigger": "Defeating this unit activates the security bulkhead leading to the chemical bay"
        },
        {
          "location": "Chemical Storage Room",
          "enemy": {
            "name": "Clockwork Sentry",
            "health": 80,
            "damage": 40,
            "weakness": "Hydraulic Wrench"
          },
          "hazard": "Rotating steam-blades",
          "pickup": {
            "name": "Corrosive Acid Vial",
            "effect": "Melts brass plating"
          },
          "trigger": "Sentry's destruction triggers a vent leak that clears the path to the reactor access"
        },
        {
          "location": "Reactor Access Tunnel",
          "enemy": {
            "name": "Gear-Smith Construct",
            "health": 100,
            "damage": 50,
            "weakness": "Corrosive Acid Vial"
          },
          "hazard": "Electrified floor plating",
          "pickup": {
            "name": "Master Keycard",
            "effect": "Overloads the main power core"
          },
          "trigger": "Construct defeat unlocks the final blast doors to the Core Chamber"
        }
      ],
      "boss": {
        "name": "Overlord Steam-Engine",
        "health": 300,
        "damage": 100,
        "weakness": "Master Keycard",
        "victory_condition": "Overload the core using the Master Keycard"
      },
      "objective": "Disable the master pressure valve to prevent city-wide explosion",
      "reward": "Prototype Steam-Engine Core"
    }
  },
  {
    "case": {
      "genre": "steampunk",
      "mood": "ominous",
      "player_class": "stormcaller",
      "target_difficulty": "hard"
    },
    "level": {
      "theme": "Industrial decay",
      "setting": "Subterranean Clockwork Factory",
      "player_weapon": "Thunder Rod",
      "player_weapon_damage": 20,
      "player_health": 100,
      "encounters": [
        {
          "location": "The Ventilation Shaft",
          "enemy": {
            "name": "Steam Automaton",
            "health": 60,
            "damage": 15,
            "weakness": "Thunder Rod"
          },
          "hazard": "Leaking high-pressure steam pipes",
          "pickup": {
            "name": "Brass Wrench",
            "effect": "Increases damage efficiency against mechanical gears"
          },
          "trigger": "Destroying the automaton clears the path into the coolant chambers"
        },
        {
          "location": "The Coolant Reservoir",
          "enemy": {
            "name": "Pipe Lurker",
            "health": 80,
            "damage": 20,
            "weakness": "Brass Wrench"
          },
          "hazard": "Electrified floor plating",
          "pickup": {
            "name": "Conductive Oil",
            "effect": "Makes dense metal surfaces highly sensitive to electricity"
          },
          "trigger": "Draining the coolant reservoir exposes the main furnace control panel"
        },
        {
          "location": "The Boiler Room",
          "enemy": {
            "name": "Steam Sentry",
            "health": 100,
            "damage": 25,
            "weakness": "Thunder Rod"
          },
          "hazard": "Rotating furnace blades",
          "pickup": {
            "name": "Overclock Chip",
            "effect": "Permanently boosts Stormcaller lightning output by 15%"
          },
          "trigger": "Overloading the circuit board with the Overclock Chip activates the elevator to the clocktower"
        }
      ],
      "boss": {
        "name": "The Grand Clockwork Sentinel",
        "health": 500,
        "damage": 50,
        "weakness": "Conductive Oil",
        "victory_condition": "Disable the central mainspring by applying the Conductive Oil and striking with the Thunder Rod"
      },
      "objective": "Sabotage the main steam generator to halt the city's clockwork movement",
      "reward": "Stormbringer's Aegis"
    }
  },
  {
    "case": {
      "genre": "steampunk",
      "mood": "desolate",
      "player_class": "chronomancer",
      "target_difficulty": "medium"
    },
    "level": {
      "theme": "Desolate Steampunk",
      "setting": "The suspended city of Coghaven",
      "player_weapon": "Chrono-Blade",
      "player_weapon_damage": 30,
      "player_health": 200,
      "encounters": [
        {
          "location": "Steam-choked alley",
          "enemy": {
            "name": "Rust-Automaton",
            "health": 100,
            "damage": 10,
            "weakness": "Chrono-Blade"
          },
          "hazard": "Leaking steam pipes",
          "pickup": {
            "name": "Brass Wrench",
            "effect": "Restores temporal armor durability"
          },
          "trigger": "Defeating the automaton lowers the primary drawbridge to the workshops"
        },
        {
          "location": "Gear-crushing workshop",
          "enemy": {
            "name": "Clockwork Sentinel",
            "health": 150,
            "damage": 15,
            "weakness": "Brass Wrench"
          },
          "hazard": "Moving heavy pistons",
          "pickup": {
            "name": "Temporal Stabilizer",
            "effect": "Stuns enemies for 5 seconds by freezing local time"
          },
          "trigger": "The sentinel's core ignition unlocks the boiler room blast door"
        },
        {
          "location": "Boiler room",
          "enemy": {
            "name": "Steam-Powered Brute",
            "health": 250,
            "damage": 25,
            "weakness": "Temporal Stabilizer"
          },
          "hazard": "Superheated steam vents",
          "pickup": {
            "name": "Clockwork Gear",
            "effect": "Used to jam mechanical bosses"
          },
          "trigger": "Defeating the brute engages the lift to the central clock tower spire"
        }
      ],
      "boss": {
        "name": "The Grand Horologist",
        "health": 500,
        "damage": 50,
        "weakness": "Clockwork Gear",
        "victory_condition": "Insert the Clockwork Gear into the master escapement during the final phase"
      },
      "objective": "Reach the pinnacle of the clock tower to reset the city's flow of time",
      "reward": "Restoration of the city's timeline"
    }
  },
  {
    "case": {
      "genre": "steampunk",
      "mood": "eerie",
      "player_class": "geomancer",
      "target_difficulty": "brutal"
    },
    "level": {
      "theme": "Eerie Steampunk",
      "setting": "The subterranean Steam-Clockwork Forge",
      "player_weapon": "Seismic Gauntlet",
      "player_weapon_damage": 15,
      "player_health": 50,
      "encounters": [
        {
          "location": "The Ventilation Shafts",
          "enemy": {
            "name": "Steam Crawler",
            "health": 30,
            "damage": 10,
            "weakness": "Seismic Gauntlet"
          },
          "hazard": "High-pressure pipe burst",
          "pickup": {
            "name": "Lubricant Oil",
            "effect": "Removes friction from mechanical joints"
          },
          "trigger": "Defeating the Crawler destroys the ventilation seal, allowing access to the Forge Core."
        },
        {
          "location": "The Forge Core",
          "enemy": {
            "name": "Rust Wraith",
            "health": 45,
            "damage": 15,
            "weakness": "Lubricant Oil"
          },
          "hazard": "Toxic smog accumulation",
          "pickup": {
            "name": "Conductive Coil",
            "effect": "Conducts rogue electricity"
          },
          "trigger": "Shattering the Wraith causes a gear collapse that opens the hallway to the Master Regulator."
        },
        {
          "location": "The Master Regulator",
          "enemy": {
            "name": "Pressure Automaton",
            "health": 60,
            "damage": 20,
            "weakness": "Conductive Coil"
          },
          "hazard": "Electrified floor plating",
          "pickup": {
            "name": "Master Key",
            "effect": "Disables the emergency lockdown protocols"
          },
          "trigger": "Downing the Automaton triggers the final overload of the security gate leading to the boss chamber."
        }
      ],
      "boss": {
        "name": "Chronos-Engine Sentinel",
        "health": 200,
        "damage": 40,
        "weakness": "Master Key",
        "victory_condition": "Insert the Master Key into the central pressure valve to depressurize the machine."
      },
      "objective": "Deactivate the ancient steam-engine core before it ruptures the city foundations.",
      "reward": "The Core of the Earth"
    }
  },
  {
    "case": {
      "genre": "steampunk",
      "mood": "serene",
      "player_class": "paladin",
      "target_difficulty": "easy"
    },
    "level": {
      "theme": "Clockwork Serenity",
      "setting": "A peaceful, floating steampunk conservatory filled with brass flora and clockwork songbirds.",
      "player_weapon": "Steam-infused Aegis Shield",
      "player_weapon_damage": 10,
      "player_health": 100,
      "encounters": [
        {
          "location": "Sunlit Conservatory Terrace",
          "enemy": {
            "name": "Brass Beetle",
            "health": 10,
            "damage": 2,
            "weakness": "Steam-infused Aegis Shield"
          },
          "hazard": "Pressurized steam jets",
          "pickup": {
            "name": "Conductive Oil",
            "effect": "Increases damage against mechanical gears"
          },
          "trigger": "Defeating the beetle unlatches the ventilation gate leading to the pond"
        },
        {
          "location": "Brass Reflecting Pond",
          "enemy": {
            "name": "Gear Sprite",
            "health": 15,
            "damage": 3,
            "weakness": "Conductive Oil"
          },
          "hazard": "Slippery clockwork floor panels",
          "pickup": {
            "name": "Heavy Lead Key",
            "effect": "Opens the main high-security engine vault"
          },
          "trigger": "Defeating the sprite drains the pond and reveals the path to the main hall"
        },
        {
          "location": "Engine Room Foyer",
          "enemy": {
            "name": "Steam Automaton",
            "health": 20,
            "damage": 3,
            "weakness": "Heavy Lead Key"
          },
          "hazard": "Rising ambient engine heat",
          "pickup": {
            "name": "Cooling Valve",
            "effect": "Dampens the boss's internal steam pressure"
          },
          "trigger": "Defeating the automaton initiates the grand door unlock sequence for the final duel"
        }
      ],
      "boss": {
        "name": "Grand Chronos Warden",
        "health": 50,
        "damage": 5,
        "weakness": "Cooling Valve",
        "victory_condition": "Deactivate the central pressure valve"
      },
      "objective": "Restore serenity to the Clockwork Sanctuary by deactivating the rogue Warden.",
      "reward": "The Eternal Mainspring"
    }
  }
]