[
  {
    "case_id": "underwater_mysterious_geomancer_medium",
    "encounters": [
      { "index": 0, "weakness": "Stone Spikes", "inventory": ["Earthshaker Staff"], "satisfied": false },
      { "index": 1, "weakness": "Magma Core", "inventory": ["Earthshaker Staff", "Magma Core"], "satisfied": true },
      { "index": 2, "weakness": "Gravity Rune", "inventory": ["Earthshaker Staff", "Magma Core", "Gravity Rune"], "satisfied": true }
    ],
    "n_satisfied": 2
  },
  {
    "case_id": "underwater_serene_beastmaster_easy",
    "encounters": [
      { "index": 0, "weakness": "Coral Staff", "inventory": ["Coral Staff"], "satisfied": true },
      { "index": 1, "weakness": "Bubble Shield", "inventory": ["Coral Staff", "Bubble Shield"], "satisfied": true },
      { "index": 2, "weakness": "Ancient Tuning Fork", "inventory": ["Coral Staff", "Bubble Shield", "Ancient Tuning Fork"], "satisfied": true }
    ],
    "n_satisfied": 3
  },
  {
    "case_id": "underwater_ominous_necromancer_hard",
    "encounters": [
      { "index": 0, "weakness": "Bone Scythe", "inventory": ["Bone Scythe"], "satisfied": true },
      { "index": 1, "weakness": "Essence of Void", "inventory": ["Bone Scythe", "Essence of Void"], "satisfied": true },
      { "index": 2, "weakness": "Abyssal Pearl", "inventory": ["Bone Scythe", "Essence of Void", "Abyssal Pearl"], "satisfied": true }
    ],
    "n_satisfied": 3
  },
  {
    "case_id": "underwater_tense_stormcaller_brutal",
    "encounters": [
      { "index": 0, "weakness": "Charged Conductivity from Stormcaller Staff", "inventory": ["Stormcaller Staff"], "satisfied": true },
      { "index": 1, "weakness": "Thermal Core", "inventory": ["Stormcaller Staff", "Thermal Core"], "satisfied": true },
      { "index": 2, "weakness": "Superconductor Rod", "inventory": ["Stormcaller Staff", "Thermal Core", "Superconductor Rod"], "satisfied": true }
    ],
    "n_satisfied": 3
  },
  {
    "case_id": "underwater_eerie_shadowblade_medium",
    "encounters": [
      { "index": 0, "weakness": "Shadowblade strikes", "inventory": ["Shadowblade"], "satisfied": true },
      { "index": 1, "weakness": "Thermal Battery impact", "inventory": ["Shadowblade", "Thermal Battery"], "satisfied": true },
      { "index": 2, "weakness": "Ancient Override Key resonance", "inventory": ["Shadowblade", "Thermal Battery", "Ancient Override Key"], "satisfied": true }
    ],
    "n_satisfied": 3
  },
  {
    "case_id": "underwater_chaotic_pyromancer_hard",
    "encounters": [
      { "index": 0, "weakness": "Thermal Flare", "inventory": ["Ignis Staff"], "satisfied": false },
      { "index": 1, "weakness": "Thermal Flare", "inventory": ["Ignis Staff", "Thermal Flare"], "satisfied": true },
      { "index": 2, "weakness": "Magma Core", "inventory": ["Ignis Staff", "Thermal Flare", "Magma Core"], "satisfied": true }
    ],
    "n_satisfied": 2
  },
  {
    "case_id": "underwater_desolate_warden_brutal",
    "encounters": [
      { "index": 0, "weakness": "Harpoon Launcher", "inventory": ["Harpoon Launcher"], "satisfied": true },
      { "index": 1, "weakness": "Super-Heated Core Fragment", "inventory": ["Harpoon Launcher", "Super-Heated Core Fragment"], "satisfied": true },
      { "index": 2, "weakness": "Sonic Resonator Module", "inventory": ["Harpoon Launcher", "Super-Heated Core Fragment", "Sonic Resonator Module"], "satisfied": true }
    ],
    "n_satisfied": 3
  },
  {
    "case_id": "underwater_whimsical_illusionist_easy",
    "encounters": [
      { "index": 0, "weakness": "Mirror Prism", "inventory": ["Phantasmal Flash"], "satisfied": false },
      { "index": 1, "weakness": "Phantasmal Flash", "inventory": ["Phantasmal Flash", "Mirror Prism"], "satisfied": true },
      { "index": 2, "weakness": "Golden Inkpot", "inventory": ["Phantasmal Flash", "Mirror Prism", "Golden Inkpot"], "satisfied": true }
    ],
    "n_satisfied": 2
  },
  {
    "case_id": "jungle_chaotic_beastmaster_hard",
    "encounters": [
      { "index": 0, "weakness": "Iron Claws", "inventory": ["Iron Claws"], "satisfied": true },
      { "index": 1, "weakness": "Fire Essence", "inventory": ["Iron Claws", "Fire Essence"], "satisfied": true },
      { "index": 2, "weakness": "Ancient Signal Horn", "inventory": ["Iron Claws", "Fire Essence", "Ancient Signal Horn"], "satisfied": true }
    ],
    "n_satisfied": 3
  },
  {
    "case_id": "jungle_mysterious_ranger_medium",
    "encounters": [
      { "index": 0, "weakness": "Longbow", "inventory": ["Longbow"], "satisfied": true },
      { "index": 1, "weakness": "Sun-Etched Amulet", "inventory": ["Longbow", "Sun-Etched Amulet"], "satisfied": true },
      { "index": 2, "weakness": "Obsidian Blade", "inventory": ["Longbow", "Sun-Etched Amulet", "Obsidian Blade"], "satisfied": true }
    ],
    "n_satisfied": 3
  },
  {
    "case_id": "jungle_tense_rogue_brutal",
    "encounters": [
      { "index": 0, "weakness": "Dagger precision", "inventory": ["Obsidian Dagger"], "satisfied": true },
      { "index": 1, "weakness": "Alchemist's Fire", "inventory": ["Obsidian Dagger", "Alchemist's Fire"], "satisfied": true },
      { "index": 2, "weakness": "Dagger precision", "inventory": ["Obsidian Dagger", "Alchemist's Fire", "Ancient Sun Amulet"], "satisfied": true }
    ],
    "n_satisfied": 3
  },
  {
    "case_id": "jungle_serene_warden_easy",
    "encounters": [
      { "index": 0, "weakness": "Iron Warden Spear", "inventory": ["Iron Warden Spear"], "satisfied": true },
      { "index": 1, "weakness": "Sun-Kissed Nectar", "inventory": ["Iron Warden Spear", "Sun-Kissed Nectar"], "satisfied": true },
      { "index": 2, "weakness": "Primal Totem", "inventory": ["Iron Warden Spear", "Sun-Kissed Nectar", "Primal Totem"], "satisfied": true }
    ],
    "n_satisfied": 3
  },
  {
    "case_id": "jungle_ominous_necromancer_hard",
    "encounters": [
      { "index": 0, "weakness": "Soul-Siphon Scythe", "inventory": ["Soul-Siphon Scythe"], "satisfied": true },
      { "index": 1, "weakness": "Ethereal Essence Vial", "inventory": ["Soul-Siphon Scythe", "Ethereal Essence Vial"], "satisfied": true },
      { "index": 2, "weakness": "Bone-Binding Talisman", "inventory": ["Soul-Siphon Scythe", "Ethereal Essence Vial", "Bone-Binding Talisman"], "satisfied": true }
    ],
    "n_satisfied": 3
  },
  {
    "case_id": "jungle_whimsical_alchemist_easy",
    "encounters": [
      { "index": 0, "weakness": "Alchemical Solvent Flask", "inventory": ["Transmutation Staff"], "satisfied": false },
      { "index": 1, "weakness": "Sonic Resonator", "inventory": ["Transmutation Staff", "Alchemical Solvent Flask"], "satisfied": false },
      { "index": 2, "weakness": "Refined Essence of Harmony", "inventory": ["Transmutation Staff", "Alchemical Solvent Flask", "Sonic Resonator"], "satisfied": false }
    ],
    "n_satisfied": 0
  },
  {
    "case_id": "jungle_eerie_chronomancer_medium",
    "encounters": [
      { "index": 0, "weakness": "Temporal Dagger", "inventory": ["Temporal Dagger"], "satisfied": true },
      { "index": 1, "weakness": "Stasis Vial", "inventory": ["Temporal Dagger", "Stasis Vial"], "satisfied": true },
      { "index": 2, "weakness": "Chronos Key", "inventory": ["Temporal Dagger", "Stasis Vial", "Chronos Key"], "satisfied": true }
    ],
    "n_satisfied": 3
  },
  {
    "case_id": "jungle_desolate_berserker_brutal",
    "encounters": [
      { "index": 0, "weakness": "Rusty Battle-Axe", "inventory": ["Rusty Battle-Axe"], "satisfied": true },
      { "index": 1, "weakness": "Jagged Obsidian Shard", "inventory": ["Rusty Battle-Axe", "Jagged Obsidian Shard"], "satisfied": true },
      { "index": 2, "weakness": "Jagged Obsidian Shard", "inventory": ["Rusty Battle-Axe", "Jagged Obsidian Shard", "Essence of the Ancient Sun"], "satisfied": true }
    ],
    "n_satisfied": 3
  }
]
