[
  {
    "case_id": "underwater_mysterious_geomancer_medium",
    "encounters": [
      {
        "index": 0,
        "weakness": "Earth-Tremor Gauntlet",
        "inventory": [
          "Earth-Tremor Gauntlet"
        ],
        "satisfied": true
      },
      {
        "index": 1,
        "weakness": "Tectonic Shard",
        "inventory": [
          "Earth-Tremor Gauntlet",
          "Tectonic Shard"
        ],
        "satisfied": true
      },
      {
        "index": 2,
        "weakness": "Abyssal Conduit",
        "inventory": [
          "Earth-Tremor Gauntlet",
          "Tectonic Shard",
          "Abyssal Conduit"
        ],
        "satisfied": true
      }
    ],
    "n_satisfied": 3
  },
  {
    "case_id": "underwater_serene_beastmaster_easy",
    "encounters": [
      {
        "index": 0,
        "weakness": "Coral Trident",
        "inventory": [
          "Coral Trident"
        ],
        "satisfied": true
      },
      {
        "index": 1,
        "weakness": "Shell Whistle",
        "inventory": [
          "Coral Trident",
          "Shell Whistle"
        ],
        "satisfied": true
      },
      {
        "index": 2,
        "weakness": "Pearly Bait",
        "inventory": [
          "Coral Trident",
          "Shell Whistle",
          "Pearly Bait"
        ],
        "satisfied": true
      }
    ],
    "n_satisfied": 3
  },
  {
    "case_id": "underwater_ominous_necromancer_hard",
    "encounters": [
      {
        "index": 0,
        "weakness": "Soul-Harvesting Scythe",
        "inventory": [
          "Soul-Harvesting Scythe"
        ],
        "satisfied": true
      },
      {
        "index": 1,
        "weakness": "Ancient Spectral Battery",
        "inventory": [
          "Soul-Harvesting Scythe",
          "Ancient Spectral Battery"
        ],
        "satisfied": true
      },
      {
        "index": 2,
        "weakness": "Crystalized Abyssal Shard",
        "inventory": [
          "Soul-Harvesting Scythe",
          "Ancient Spectral Battery",
          "Crystalized Abyssal Shard"
        ],
        "satisfied": true
      }
    ],
    "n_satisfied": 3
  },
  {
    "case_id": "underwater_tense_stormcaller_brutal",
    "encounters": [
      {
        "index": 0,
        "weakness": "Ion Staff",
        "inventory": [
          "Ion Staff"
        ],
        "satisfied": true
      },
      {
        "index": 1,
        "weakness": "Conductive Fluid",
        "inventory": [
          "Ion Staff",
          "Conductive Fluid"
        ],
        "satisfied": true
      },
      {
        "index": 2,
        "weakness": "High-Voltage Coil",
        "inventory": [
          "Ion Staff",
          "Conductive Fluid",
          "High-Voltage Coil"
        ],
        "satisfied": true
      }
    ],
    "n_satisfied": 3
  },
  {
    "case_id": "underwater_eerie_shadowblade_medium",
    "encounters": [
      {
        "index": 0,
        "weakness": "Void-edged Dagger",
        "inventory": [
          "Void-edged Dagger"
        ],
        "satisfied": true
      },
      {
        "index": 1,
        "weakness": "Bioluminescent Pearl",
        "inventory": [
          "Void-edged Dagger",
          "Bioluminescent Pearl"
        ],
        "satisfied": true
      },
      {
        "index": 2,
        "weakness": "Ancient Pressure Key",
        "inventory": [
          "Void-edged Dagger",
          "Bioluminescent Pearl",
          "Ancient Pressure Key"
        ],
        "satisfied": true
      }
    ],
    "n_satisfied": 3
  },
  {
    "case_id": "underwater_chaotic_pyromancer_hard",
    "encounters": [
      {
        "index": 0,
        "weakness": "Thermal Lance",
        "inventory": [
          "Thermal Lance"
        ],
        "satisfied": true
      },
      {
        "index": 1,
        "weakness": "Pressurized Magma Core",
        "inventory": [
          "Thermal Lance",
          "Pressurized Magma Core"
        ],
        "satisfied": true
      },
      {
        "index": 2,
        "weakness": "Ancient Cooling Agent",
        "inventory": [
          "Thermal Lance",
          "Pressurized Magma Core",
          "Ancient Cooling Agent"
        ],
        "satisfied": true
      }
    ],
    "n_satisfied": 3
  },
  {
    "case_id": "underwater_desolate_warden_brutal",
    "encounters": [
      {
        "index": 0,
        "weakness": "Harpoon Lance",
        "inventory": [
          "Harpoon Lance"
        ],
        "satisfied": true
      },
      {
        "index": 1,
        "weakness": "Thermal Battery",
        "inventory": [
          "Harpoon Lance",
          "Thermal Battery"
        ],
        "satisfied": true
      },
      {
        "index": 2,
        "weakness": "Sonic Emitter",
        "inventory": [
          "Harpoon Lance",
          "Thermal Battery",
          "Sonic Emitter"
        ],
        "satisfied": true
      }
    ],
    "n_satisfied": 3
  },
  {
    "case_id": "underwater_whimsical_illusionist_easy",
    "encounters": [
      {
        "index": 0,
        "weakness": "Prism Wand",
        "inventory": [
          "Prism Wand"
        ],
        "satisfied": true
      },
      {
        "index": 1,
        "weakness": "Sea-Crystal Lens",
        "inventory": [
          "Prism Wand",
          "Sea-Crystal Lens"
        ],
        "satisfied": true
      },
      {
        "index": 2,
        "weakness": "Golden Siren Scale",
        "inventory": [
          "Prism Wand",
          "Sea-Crystal Lens",
          "Golden Siren Scale"
        ],
        "satisfied": true
      }
    ],
    "n_satisfied": 3
  },
  {
    "case_id": "jungle_chaotic_beastmaster_hard",
    "encounters": [
      {
        "index": 0,
        "weakness": "Iron Claw",
        "inventory": [
          "Iron Claw"
        ],
        "satisfied": true
      },
      {
        "index": 1,
        "weakness": "Fermented Berry",
        "inventory": [
          "Iron Claw",
          "Fermented Berry"
        ],
        "satisfied": true
      },
      {
        "index": 2,
        "weakness": "Ancient Totem",
        "inventory": [
          "Iron Claw",
          "Fermented Berry",
          "Ancient Totem"
        ],
        "satisfied": true
      }
    ],
    "n_satisfied": 3
  },
  {
    "case_id": "jungle_mysterious_ranger_medium",
    "encounters": [
      {
        "index": 0,
        "weakness": "Longbow",
        "inventory": [
          "Longbow"
        ],
        "satisfied": true
      },
      {
        "index": 1,
        "weakness": "Sun-Crystal",
        "inventory": [
          "Longbow",
          "Sun-Crystal"
        ],
        "satisfied": true
      },
      {
        "index": 2,
        "weakness": "Sacred Relic Arrow",
        "inventory": [
          "Longbow",
          "Sun-Crystal",
          "Sacred Relic Arrow"
        ],
        "satisfied": true
      }
    ],
    "n_satisfied": 3
  },
  {
    "case_id": "jungle_tense_rogue_brutal",
    "encounters": [
      {
        "index": 0,
        "weakness": "Poisoned Dagger",
        "inventory": [
          "Poisoned Dagger"
        ],
        "satisfied": true
      },
      {
        "index": 1,
        "weakness": "Heavy Vine Cleaver",
        "inventory": [
          "Poisoned Dagger",
          "Heavy Vine Cleaver"
        ],
        "satisfied": true
      },
      {
        "index": 2,
        "weakness": "Ancient Ritual Incense",
        "inventory": [
          "Poisoned Dagger",
          "Heavy Vine Cleaver",
          "Ancient Ritual Incense"
        ],
        "satisfied": true
      }
    ],
    "n_satisfied": 3
  },
  {
    "case_id": "jungle_serene_warden_easy",
    "encounters": [
      {
        "index": 0,
        "weakness": "Warden's Staff",
        "inventory": [
          "Warden's Staff"
        ],
        "satisfied": true
      },
      {
        "index": 1,
        "weakness": "Sunlight Crystal",
        "inventory": [
          "Warden's Staff",
          "Sunlight Crystal"
        ],
        "satisfied": true
      },
      {
        "index": 2,
        "weakness": "Dew of Life",
        "inventory": [
          "Warden's Staff",
          "Sunlight Crystal",
          "Dew of Life"
        ],
        "satisfied": true
      }
    ],
    "n_satisfied": 3
  },
  {
    "case_id": "jungle_ominous_necromancer_hard",
    "encounters": [
      {
        "index": 0,
        "weakness": "Spectral Scythe",
        "inventory": [
          "Spectral Scythe"
        ],
        "satisfied": true
      },
      {
        "index": 1,
        "weakness": "Soul Shard",
        "inventory": [
          "Spectral Scythe",
          "Soul Shard"
        ],
        "satisfied": true
      },
      {
        "index": 2,
        "weakness": "Poisoned Dagger",
        "inventory": [
          "Spectral Scythe",
          "Soul Shard",
          "Poisoned Dagger"
        ],
        "satisfied": true
      }
    ],
    "n_satisfied": 3
  },
  {
    "case_id": "jungle_whimsical_alchemist_easy",
    "encounters": [
      {
        "index": 0,
        "weakness": "Corrosive Acid Flask",
        "inventory": [
          "Corrosive Acid Flask"
        ],
        "satisfied": true
      },
      {
        "index": 1,
        "weakness": "Frost-Essence Vials",
        "inventory": [
          "Corrosive Acid Flask",
          "Frost-Essence Vials"
        ],
        "satisfied": true
      },
      {
        "index": 2,
        "weakness": "Sonic Crystal",
        "inventory": [
          "Corrosive Acid Flask",
          "Frost-Essence Vials",
          "Sonic Crystal"
        ],
        "satisfied": true
      }
    ],
    "n_satisfied": 3
  },
  {
    "case_id": "jungle_eerie_chronomancer_medium",
    "encounters": [
      {
        "index": 0,
        "weakness": "Chrono-Blade",
        "inventory": [
          "Chrono-Blade"
        ],
        "satisfied": true
      },
      {
        "index": 1,
        "weakness": "Time-Sand Vial",
        "inventory": [
          "Chrono-Blade",
          "Time-Sand Vial"
        ],
        "satisfied": true
      },
      {
        "index": 2,
        "weakness": "Sun-Dial Shard",
        "inventory": [
          "Chrono-Blade",
          "Time-Sand Vial",
          "Sun-Dial Shard"
        ],
        "satisfied": true
      }
    ],
    "n_satisfied": 3
  },
  {
    "case_id": "jungle_desolate_berserker_brutal",
    "encounters": [
      {
        "index": 0,
        "weakness": "Obsidian Great-Axe",
        "inventory": [
          "Obsidian Great-Axe"
        ],
        "satisfied": true
      },
      {
        "index": 1,
        "weakness": "Sun-Crystal",
        "inventory": [
          "Obsidian Great-Axe",
          "Sun-Crystal"
        ],
        "satisfied": true
      },
      {
        "index": 2,
        "weakness": "Sacred Resin",
        "inventory": [
          "Obsidian Great-Axe",
          "Sun-Crystal",
          "Sacred Resin"
        ],
        "satisfied": true
      }
    ],
    "n_satisfied": 3
  }
]
